go_to_github/__init__.py
go_to_github/main.py
go_to_github/settings.py
go_to_github-0.0.18.dist-info/entry_points.txt
go_to_github-0.0.18.dist-info/LICENSE
go_to_github-0.0.18.dist-info/WHEEL
go_to_github-0.0.18.dist-info/METADATA
go_to_github-0.0.18.dist-info/RECORD
