Metadata-Version: 2.1
Name: go_to_github
Version: 0.0.18
Summary: `go_to_github` is a tool to test whether `github.com` is reachable right now. If not, it will work it out automatically.
Home-page: https://github.com/KateWang2016/go_to_github
Keywords: python, github, web connection, local host
Author: Kate Wang
Author-email: kate.wang2018@gmail.com
Requires-Python: >=3.7
Classifier: License :: OSI Approved :: MIT License
Requires-Dist: lxml
Requires-Dist: fake_user_agent
Requires-Dist: requests
